faff_cli/__init__.py
faff_cli/exceptions.py
faff_cli/field.py
faff_cli/filtering.py
faff_cli/id.py
faff_cli/intent.py
faff_cli/log.py
faff_cli/main.py
faff_cli/output.py
faff_cli/plan.py
faff_cli/plugin.py
faff_cli/query.py
faff_cli/reflect.py
faff_cli/remote.py
faff_cli/session.py
faff_cli/sql.py
faff_cli/start.py
faff_cli/timesheet.py
faff_cli/utils.py
faff_cli/ui/__init__.py
faff_cli/ui/fuzzy_select.py
faff_cli-0.1.9.dist-info/licenses/LICENSE
faff_cli-0.1.9.dist-info/METADATA
faff_cli-0.1.9.dist-info/WHEEL
faff_cli-0.1.9.dist-info/entry_points.txt
faff_cli-0.1.9.dist-info/top_level.txt
faff_cli-0.1.9.dist-info/RECORD
