Metadata-Version: 2.4
Name: faff-cli
Version: 0.1.9
Summary: A local-first time tracking CLI with decentralized protocol aspirations.
Author-email: Thomas Lant <thomas@lant.uk>
License: AGPL-3.0-or-later
Requires-Python: >=3.11
License-File: LICENSE
Requires-Dist: faff-core>=0.1.16
Requires-Dist: typer[all]
Requires-Dist: rich
Requires-Dist: python-slugify
Requires-Dist: titlecase
Requires-Dist: prompt-toolkit
Requires-Dist: pfzy
Requires-Dist: dateparser
Requires-Dist: humanize
Requires-Dist: toml
Provides-Extra: dev
Requires-Dist: pytest>=7.0; extra == "dev"
Requires-Dist: pytest-cov>=4.0; extra == "dev"
Requires-Dist: pytest-mock>=3.10; extra == "dev"
Requires-Dist: mypy>=1.0; extra == "dev"
Requires-Dist: types-toml; extra == "dev"
Dynamic: license-file
